humailib/__init__.py
humailib/bayesian_helper.py
humailib/clang_webhook_helper.py
humailib/cloud_tools.py
humailib/copernica.py
humailib/customer_id.py
humailib/data_processing.py
humailib/email_features.py
humailib/functions_gherkin.py
humailib/ga_tools.py
humailib/graph_based_prod_recommend.py
humailib/hasher.py
humailib/hasher_no_deps.py
humailib/helpers.py
humailib/info.py
humailib/lifecycle.py
humailib/lstm.py
humailib/magento.py
humailib/mailchimp.py
humailib/model_eval.py
humailib/pipeline_builder.py
humailib/product_category_model.py
humailib/product_launch_customer_ranking.py
humailib/propensity.py
humailib/proportional_hazards_model.py
humailib/ranking_model.py
humailib/sequential_model.py
humailib/sequential_model_helper.py
humailib/transaction_features.py
humailib/transformers.py
humailib/utils.py
humailib-1.0.36.dist-info/METADATA
humailib-1.0.36.dist-info/WHEEL
humailib-1.0.36.dist-info/top_level.txt
humailib-1.0.36.dist-info/RECORD
