Metadata-Version: 2.1
Name: humailib
Version: 1.0.36
Summary: HUMAI data science framework
Home-page: UNKNOWN
Author: HUMAI Limited
Author-email: willem@humai.nl
License: UNKNOWN
Platform: UNKNOWN
Requires-Dist: pandas-gbq
Requires-Dist: pathlib
Requires-Dist: google-cloud-datastore
Requires-Dist: google-cloud-bigquery
Requires-Dist: google-cloud-storage
Requires-Dist: tqdm
Requires-Dist: google-cloud-bigquery-storage
Requires-Dist: pyarrow
Requires-Dist: pandas (==1.0.0)
